tago/__init__.py
tago/account/__init__.py
tago/account/_share.py
tago/account/accessManagement.py
tago/account/actions.py
tago/account/analysis.py
tago/account/buckets.py
tago/account/connector.py
tago/account/dashboards.py
tago/account/dashboards_widgets.py
tago/account/devices.py
tago/account/explore.py
tago/account/files.py
tago/account/integration_network.py
tago/account/notifications.py
tago/account/paymentHistory.py
tago/account/paymentMethods.py
tago/account/plan.py
tago/account/profiles.py
tago/account/run.py
tago/account/service_authorization.py
tago/account/socket.py
tago/account/tags.py
tago/account/template.py
tago/analysis/__init__.py
tago/authorization/__init__.py
tago/connector/__init__.py
tago/device/__init__.py
tago/internal/__init__.py
tago/run_user/__init__.py
tago/services/__init__.py
tago/services/attachment.py
tago/services/console.py
tago/services/emailService.py
tago/services/mqtt.py
tago/services/notification.py
tago/services/sms.py
tago/utils/__init__.py
tago/utils/env_to_obj.py
tago/utils/getTokenByName.py
tago/utils/version.py
tago-3.1.1.dist-info/LICENSE.md
tago-3.1.1.dist-info/METADATA
tago-3.1.1.dist-info/WHEEL
tago-3.1.1.dist-info/top_level.txt
tago-3.1.1.dist-info/RECORD
