Metadata-Version: 2.1
Name: tago
Version: 3.1.1
Summary: Official Python lib for TagoIO
Home-page: https://github.com/tago-io/tago-sdk-python
Author: Tago LLC
Author-email: dev@tago.io
License: Apache License
Keywords: tago tagoio develop iot sdk analysis device
Classifier: Development Status :: 5 - Production/Stable
Classifier: License :: OSI Approved :: Apache Software License
Classifier: Programming Language :: Python :: 3 :: Only
Classifier: Topic :: Software Development :: Libraries :: Python Modules
Requires-Python: >=3.6
License-File: LICENSE.md
Requires-Dist: python-socketio (==5.7.2)
Requires-Dist: requests (==2.28.2)
Requires-Dist: promise (==2.3)
Requires-Dist: websockets (==9.1)
Requires-Dist: aiohttp (==3.8.4)
